phylm/__init__.py
phylm/__main__.py
phylm/clients/__init__.py
phylm/clients/tmdb.py
phylm/errors.py
phylm/phylm.py
phylm/py.typed
phylm/sources/__init__.py
phylm/sources/imdb.py
phylm/sources/mtc.py
phylm/sources/rt.py
phylm/sources/tmdb.py
phylm/tools.py
phylm/utils/__init__.py
phylm/utils/web.py
phylm-6.1.4.dist-info/LICENSE.txt
phylm-6.1.4.dist-info/LICENSE.rst
phylm-6.1.4.dist-info/WHEEL
phylm-6.1.4.dist-info/entry_points.txt
phylm-6.1.4.dist-info/METADATA
phylm-6.1.4.dist-info/RECORD
