Metadata-Version: 2.1
Name: phylm
Version: 6.1.4
Summary: Phylm
Home-page: https://github.com/dbatten5/phylm
License: MIT
Author: Dom Batten
Author-email: dominic.batten@googlemail.com
Requires-Python: >=3.8.1,<4.0.0
Classifier: Development Status :: 5 - Production/Stable
Classifier: License :: OSI Approved :: MIT License
Classifier: Programming Language :: Python :: 3
Classifier: Programming Language :: Python :: 3.9
Classifier: Programming Language :: Python :: 3.10
Classifier: Programming Language :: Python :: 3.11
Classifier: Programming Language :: Python :: 3.8
Classifier: Programming Language :: Python :: 3.9
Requires-Dist: aiohttp (>=3.8.1,<4.0.0)
Requires-Dist: beautifulsoup4 (>=4.10.0,<5.0.0)
Requires-Dist: cinemagoer (>=2023.05.01,<2024.0.0)
Requires-Dist: click (>=8.0.1,<9.0.0)
Requires-Dist: requests (>=2.26.0,<3.0.0)
Project-URL: Changelog, https://github.com/dbatten5/phylm/releases
Project-URL: Documentation, https://dbatten5.github.io/phylm
Project-URL: Repository, https://github.com/dbatten5/phylm
